flasksqlalchemybasemodel/__init__.py
flasksqlalchemybasemodel/src.py
flasksqlalchemybasemodel-1.2.0.dist-info/LICENSE
flasksqlalchemybasemodel-1.2.0.dist-info/METADATA
flasksqlalchemybasemodel-1.2.0.dist-info/WHEEL
flasksqlalchemybasemodel-1.2.0.dist-info/RECORD
