Metadata-Version: 2.1
Name: FlaskSQLAlchemyBaseModel
Version: 1.2.0
Summary: FlaskSQLAlchemyBaseModel package provides a foundation for building SQLAlchemy-based ORM models in a Flask application. It offers common functionality required by most models, including automatic handling of unique identifiers, timestamps, and convenience methods for CRUD operations. This package streamlines the development process by offering a consistent and reusable base class for database models, ensuring that every model inherits essential features and reduces boilerplate code.
License: MIT
Author: AnozieChibuike
Author-email: chibuikeanozie0@gmail.com
Requires-Python: >=3.10,<4.0
Classifier: License :: OSI Approved :: MIT License
Classifier: Programming Language :: Python :: 3
Classifier: Programming Language :: Python :: 3.10
Classifier: Programming Language :: Python :: 3.11
Requires-Dist: flask (>=3.0.0,<4.0.0)
Requires-Dist: flask-sqlalchemy (>=3.1.1,<4.0.0)
Requires-Dist: sqlalchemy (>=2.0.0,<3.0.0)
